panda_python_kit/__init__.py
panda_python_kit/comm/__init__.py
panda_python_kit/comm/comm.py
panda_python_kit/comm/result_model.py
panda_python_kit/data/IP2LOCATION-LITE-DB3.BIN
panda_python_kit/data/__init__.py
panda_python_kit/dt/__init__.py
panda_python_kit/dt/util.py
panda_python_kit/qr/__init__.py
panda_python_kit/qr/easing.py
panda_python_kit/scrapy/__init__.py
panda_python_kit/scrapy/ip_location.py
panda_python_kit/scrapy/user_agent.py
panda_python_kit/scrapy/mw/__init__.py
panda_python_kit/scrapy/mw/random_user_agent.py
panda_python_kit-0.0.40.dist-info/LICENSE
panda_python_kit-0.0.40.dist-info/METADATA
panda_python_kit-0.0.40.dist-info/WHEEL
panda_python_kit-0.0.40.dist-info/top_level.txt
panda_python_kit-0.0.40.dist-info/RECORD
