Metadata-Version: 2.2
Name: panda-python-kit
Version: 0.0.40
Summary: panda python kit
Home-page: https://github.com/zhaojiedi1992/panda_python_kit
Author: zhaojiedi
Author-email: 1072892917@qq.com
License: MIT
Platform: any
Classifier: Development Status :: 4 - Beta
Classifier: License :: OSI Approved :: Apache Software License
Classifier: Operating System :: OS Independent
Classifier: Programming Language :: Python :: 3
Classifier: Programming Language :: Python :: 3.6
Classifier: Programming Language :: Python :: 3.7
Classifier: Programming Language :: Python :: 3.8
Classifier: Programming Language :: Python :: 3.9
Classifier: Programming Language :: Python :: 3.10
Requires-Python: >=3.6
License-File: LICENSE
Requires-Dist: requests
Requires-Dist: python-dateutil
Requires-Dist: pandas
Requires-Dist: build
Requires-Dist: fake_useragent
Requires-Dist: ip2location
Dynamic: author
Dynamic: author-email
Dynamic: classifier
Dynamic: description
Dynamic: description-content-type
Dynamic: home-page
Dynamic: license
Dynamic: platform
Dynamic: requires-dist
Dynamic: requires-python
Dynamic: summary
